zipmanager/Exceptions.py
zipmanager/File.py
zipmanager/__init__.py
zipmanager/files.py
zipmanager/main.py
zipmanager-0.6.1.dist-info/licenses/LICENSE
zipmanager-0.6.1.dist-info/METADATA
zipmanager-0.6.1.dist-info/WHEEL
zipmanager-0.6.1.dist-info/top_level.txt
zipmanager-0.6.1.dist-info/RECORD
