Metadata-Version: 2.4
Name: zipmanager
Version: 0.6.1
Summary: Allows you to manage zip folders as data
Author: SimplePythonCoder
License-Expression: MIT
Project-URL: Homepage, https://github.com/SimplePythonCoder/zipmanager
Project-URL: Source, https://github.com/SimplePythonCoder/zipmanager
Project-URL: Changelog, https://github.com/SimplePythonCoder/zipmanager/blob/main/CHANGELOG.md
Project-URL: Documentation, https://github.com/SimplePythonCoder/zipmanager/wiki
Project-URL: Issues, https://github.com/SimplePythonCoder/zipmanager/issues
Keywords: zip,zipfile
Classifier: Development Status :: 5 - Production/Stable
Classifier: Intended Audience :: Developers
Classifier: Programming Language :: Python :: 3.11
Classifier: Operating System :: Microsoft :: Windows :: Windows 10
Classifier: Topic :: Utilities
Requires-Python: >=3.11
License-File: LICENSE
Dynamic: license-file
